saturnin/_scripts/__init__.py
saturnin/_scripts/bundlerun.py
saturnin/_scripts/cli.py
saturnin/_scripts/completers.py
saturnin/_scripts/daemon.py
saturnin/_scripts/repl.py
saturnin/_scripts/svcrun.py
saturnin/_scripts/commands/__init__.py
saturnin/_scripts/commands/daemons.py
saturnin/_scripts/commands/oids.py
saturnin/_scripts/commands/pkg.py
saturnin/_scripts/commands/recipes.py
saturnin/_scripts/commands/site.py
saturnin/base/__init__.py
saturnin/base/component.py
saturnin/base/config.py
saturnin/base/transport.py
saturnin/base/types.py
saturnin/component/__init__.py
saturnin/component/apps.py
saturnin/component/bundle.py
saturnin/component/client.py
saturnin/component/controller.py
saturnin/component/micro.py
saturnin/component/recipe.py
saturnin/component/registry.py
saturnin/component/service.py
saturnin/component/single.py
saturnin/lib/__init__.py
saturnin/lib/console.py
saturnin/lib/daemon.py
saturnin/lib/metadata.py
saturnin/lib/data/__init__.py
saturnin/lib/data/filter.py
saturnin/lib/data/onepipe.py
saturnin/protocol/__init__.py
saturnin/protocol/fbdp.py
saturnin/protocol/fbsp.py
saturnin/protocol/iccp.py
saturnin-0.10.0.dist-info/METADATA
saturnin-0.10.0.dist-info/WHEEL
saturnin-0.10.0.dist-info/entry_points.txt
saturnin-0.10.0.dist-info/licenses/LICENSE
saturnin-0.10.0.dist-info/RECORD
