Metadata-Version: 2.4
Name: saturnin
Version: 0.10.0
Summary: Firebird Butler platform for Python
Project-URL: Home, http://firebirdsql.org/en/saturnin/
Project-URL: Documentation, https://saturnin.rtfd.io
Project-URL: Issues, https://github.com/FirebirdSQL/saturnin/issues
Project-URL: Funding, https://github.com/sponsors/pcisar
Project-URL: Source, https://github.com/FirebirdSQL/saturnin
Author-email: Pavel Cisar <pcisar@users.sourceforge.net>
License: MIT License
License-File: LICENSE
Keywords: Butler,Firebird,Platform,Saturnin,ZeroMQ
Classifier: Development Status :: 4 - Beta
Classifier: Intended Audience :: Developers
Classifier: Intended Audience :: System Administrators
Classifier: License :: OSI Approved :: MIT License
Classifier: Operating System :: MacOS
Classifier: Operating System :: Microsoft :: Windows
Classifier: Operating System :: POSIX :: Linux
Classifier: Programming Language :: Python :: 3 :: Only
Classifier: Programming Language :: Python :: 3.11
Classifier: Programming Language :: Python :: 3.12
Classifier: Programming Language :: Python :: 3.13
Classifier: Topic :: Database
Classifier: Topic :: Software Development
Classifier: Topic :: Software Development :: Libraries
Classifier: Topic :: Software Development :: Libraries :: Application Frameworks
Classifier: Topic :: Software Development :: Object Brokering
Classifier: Topic :: System :: Logging
Classifier: Topic :: System :: Monitoring
Classifier: Topic :: System :: Systems Administration
Requires-Python: >=3.11
Requires-Dist: firebird-base~=2.0
Requires-Dist: firebird-butler-protobuf~=2.0
Requires-Dist: firebird-uuid~=1.0
Requires-Dist: packaging~=25.0
Requires-Dist: prompt-toolkit~=3.0
Requires-Dist: protobuf~=5.29
Requires-Dist: psutil~=7.0
Requires-Dist: pyzmq~=26.4
Requires-Dist: rich~=14.0
Requires-Dist: tomli-w~=1.2
Requires-Dist: typer~=0.15
Provides-Extra: firebird
Requires-Dist: firebird-driver~=2.0; extra == 'firebird'
Requires-Dist: firebird-lib~=2.0; extra == 'firebird'
